Metadata-Version: 1.0
Name: cos-migrate-tool-test
Version: 0.1.0
Summary: migrate tool for object storage services
Home-page: https://www.qcloud.com/
Author: liuchang
Author-email: liuchang0812@gmail.com
License: MIT
Platform: UNKNOWN
